{
  "embed_url": "https://api.yaoyuan.org/embed",
  "description": "Showing the last 7 days of Cloudflare unique visitor geography.",
  "generated_at": "2026-06-28T02:00:10.710Z",
  "range_days": 7,
  "total_uniques": 2174,
  "total_requests": 16521,
  "countries": [
    {
      "name": "France",
      "requests": 4427,
      "share": 26.8
    },
    {
      "name": "Australia",
      "requests": 3873,
      "share": 23.4
    },
    {
      "name": "United States",
      "requests": 2598,
      "share": 15.7
    },
    {
      "name": "Netherlands",
      "requests": 1826,
      "share": 11.1
    },
    {
      "name": "Brazil",
      "requests": 1456,
      "share": 8.8
    },
    {
      "name": "Singapore",
      "requests": 1069,
      "share": 6.5
    },
    {
      "name": "South Korea",
      "requests": 787,
      "share": 4.8
    },
    {
      "name": "Poland",
      "requests": 485,
      "share": 2.9
    }
  ],
  "map_countries": [
    {
      "name": "France",
      "requests": 4427
    },
    {
      "name": "Australia",
      "requests": 3873
    },
    {
      "name": "United States",
      "requests": 2598
    },
    {
      "name": "Netherlands",
      "requests": 1826
    },
    {
      "name": "Brazil",
      "requests": 1456
    },
    {
      "name": "Singapore",
      "requests": 1069
    },
    {
      "name": "South Korea",
      "requests": 787
    },
    {
      "name": "Poland",
      "requests": 485
    },
    {
      "name": "Germany",
      "requests": 459
    },
    {
      "name": "Canada",
      "requests": 438
    },
    {
      "name": "Norway",
      "requests": 357
    },
    {
      "name": "Ireland",
      "requests": 352
    },
    {
      "name": "Japan",
      "requests": 341
    },
    {
      "name": "China",
      "requests": 307
    },
    {
      "name": "Sweden",
      "requests": 241
    },
    {
      "name": "Switzerland",
      "requests": 213
    },
    {
      "name": "Spain",
      "requests": 211
    },
    {
      "name": "United Kingdom",
      "requests": 180
    },
    {
      "name": "India",
      "requests": 126
    },
    {
      "name": "Italy",
      "requests": 75
    },
    {
      "name": "Russia",
      "requests": 62
    },
    {
      "name": "Finland",
      "requests": 41
    },
    {
      "name": "Vietnam",
      "requests": 32
    },
    {
      "name": "Indonesia",
      "requests": 29
    },
    {
      "name": "Czech Republic",
      "requests": 19
    },
    {
      "name": "Argentina",
      "requests": 15
    },
    {
      "name": "Bangladesh",
      "requests": 12
    },
    {
      "name": "Ukraine",
      "requests": 11
    },
    {
      "name": "Pakistan",
      "requests": 10
    },
    {
      "name": "Mexico",
      "requests": 9
    },
    {
      "name": "Belgium",
      "requests": 9
    },
    {
      "name": "Chile",
      "requests": 8
    },
    {
      "name": "Colombia",
      "requests": 8
    },
    {
      "name": "Romania",
      "requests": 6
    },
    {
      "name": "South Africa",
      "requests": 5
    },
    {
      "name": "Saudi Arabia",
      "requests": 4
    },
    {
      "name": "Nigeria",
      "requests": 3
    },
    {
      "name": "Kenya",
      "requests": 3
    },
    {
      "name": "United Arab Emirates",
      "requests": 3
    },
    {
      "name": "New Zealand",
      "requests": 2
    },
    {
      "name": "Philippines",
      "requests": 1
    },
    {
      "name": "Turkey",
      "requests": 1
    },
    {
      "name": "Portugal",
      "requests": 1
    },
    {
      "name": "Thailand",
      "requests": 1
    },
    {
      "name": "Austria",
      "requests": 1
    },
    {
      "name": "Israel",
      "requests": 1
    }
  ]
}